setup.py
racm_distributions/Binomialdistribution.py
racm_distributions/Gaussiandistribution.py
racm_distributions/Generaldistribution.py
racm_distributions/__init__.py
racm_distributions.egg-info/PKG-INFO
racm_distributions.egg-info/SOURCES.txt
racm_distributions.egg-info/dependency_links.txt
racm_distributions.egg-info/not-zip-safe
racm_distributions.egg-info/top_level.txt