Metadata-Version: 1.0
Name: racm-distributions
Version: 0.1
Summary: Gaussian distributions
Home-page: UNKNOWN
Author: Raquel Cerda
Author-email: UNKNOWN
License: UNKNOWN
Platform: UNKNOWN
